MANIFEST.in
README.rst
TITLE.txt
lh-agpl3-LICENSE.txt
setup.py
./bin/uxpProcessAgentOutcomes.py
bisos2/__init__.py
bisos2.gossonot.egg-info/PKG-INFO
bisos2.gossonot.egg-info/SOURCES.txt
bisos2.gossonot.egg-info/dependency_links.txt
bisos2.gossonot.egg-info/namespace_packages.txt
bisos2.gossonot.egg-info/not-zip-safe
bisos2.gossonot.egg-info/requires.txt
bisos2.gossonot.egg-info/top_level.txt
bisos2/gossonot/__init__.py
bisos2/gossonot/gossonotPkgThis.py